HiCHap/AllelicSpecificity.py
HiCHap/StructureFind.py
HiCHap/__init__.py
HiCHap/bamProcess.py
HiCHap/fastqPlus.py
HiCHap/filtering.py
HiCHap/genome.py
HiCHap/mapping.py
HiCHap/matrixBuilding.py
HiCHap-1.6.data/scripts/hichap
HiCHap-1.6.dist-info/LICENSE
HiCHap-1.6.dist-info/METADATA
HiCHap-1.6.dist-info/WHEEL
HiCHap-1.6.dist-info/top_level.txt
HiCHap-1.6.dist-info/RECORD
