Metadata-Version: 2.1
Name: HiCHap
Version: 1.6
Summary: An integrated package to process diploid Hi-C data
Home-page: https://github.com/Prayforhanluo/HiCHap_master
Author: Han Luo
Author-email: hluo_lc@outlook.com
License: UNKNOWN
Platform: UNKNOWN
Classifier: Programming Language :: Python
Classifier: Intended Audience :: Science/Research
Classifier: Topic :: Scientific/Engineering :: Bio-Informatics
Classifier: License :: OSI Approved :: GNU General Public License v3 or later (GPLv3+)
